bulk_copy/__init__.py
bulk_copy/engines/__init__.py
bulk_copy/engines/base.py
bulk_copy/engines/postgresql.py
bulk_copy/manager.py
bulk_copy/utils.py
django_bulk_copy-0.2.0.dist-info/LICENSE
django_bulk_copy-0.2.0.dist-info/METADATA
django_bulk_copy-0.2.0.dist-info/WHEEL
django_bulk_copy-0.2.0.dist-info/RECORD
