Metadata-Version: 2.1
Name: django-bulk-copy
Version: 0.2.0
Summary: Faster way to create your models in Django
Keywords: django,postgres,django-bulk-copy,bulk,t-sql
Author: Ahmet Burak Ozyurt
Author-email: ahmetbozyurtt@gmail.com
Maintainer: Ahmet Burak Ozyurt
Maintainer-email: ahmetbozyurtt@gmail.com
Requires-Python: >=3.9,<4.0
Classifier: Development Status :: 4 - Beta
Classifier: License :: OSI Approved :: MIT License
Classifier: Natural Language :: English
Classifier: Operating System :: OS Independent
Classifier: Programming Language :: Python :: 3
Classifier: Programming Language :: Python :: 3.9
Classifier: Programming Language :: Python :: 3.10
Classifier: Programming Language :: Python :: 3.11
Classifier: Programming Language :: Python :: 3.12
Classifier: Programming Language :: Python :: 3.8
Classifier: Topic :: Software Development :: Libraries :: Python Modules
Provides-Extra: postgres
Requires-Dist: django (>=3)
Requires-Dist: psycopg2 (>=2.9,<3.0) ; extra == "postgres"
Project-URL: documentation, https://github.com/ahmetveburak/django-bulk-copy/blob/main/README.md
Project-URL: homepage, https://github.com/ahmetveburak/django-bulk-copy
Project-URL: repository, https://github.com/ahmetveburak/django-bulk-copy
